ndx_fllab_novela/__init__.py
ndx_fllab_novela/apparatus.py
ndx_fllab_novela/header_device.py
ndx_fllab_novela/ntrode.py
ndx_fllab_novela/probe.py
ndx_fllab_novela/spec/ndx-fllab-novela.extensions.yaml
ndx_fllab_novela/spec/ndx-fllab-novela.namespace.yaml
tests/__init__.py
tests/test_apparatus.py
tests/test_edge.py
tests/test_header_device.py
tests/test_node.py
tests/test_ntrode.py
tests/test_probe.py
ndx_fllab_novela-0.0.7.dist-info/LICENSE.txt
ndx_fllab_novela-0.0.7.dist-info/METADATA
ndx_fllab_novela-0.0.7.dist-info/WHEEL
ndx_fllab_novela-0.0.7.dist-info/top_level.txt
ndx_fllab_novela-0.0.7.dist-info/RECORD
