Metadata-Version: 2.1
Name: ndx-fllab-novela
Version: 0.0.7
Summary: NovelaNeurotechnologies Namespaces
Home-page: UNKNOWN
Author: NovelaDevops
Author-email: devops@novelaneuro.com
License: BSD 3-Clause
Platform: UNKNOWN
Classifier: Intended Audience :: Developers
Classifier: Intended Audience :: Science/Research
Requires-Dist: hdmf (==1.6.1)
Requires-Dist: pynwb (==1.3.0)
